funland/__init__.py
funland/containers.py
funland/wrappers.py
funland-0.0.0a0.dist-info/WHEEL
funland-0.0.0a0.dist-info/METADATA
funland-0.0.0a0.dist-info/RECORD
