Metadata-Version: 2.1
Name: funland
Version: 0.0.0a0
Summary: Function programming in python
Requires-Python: >= 3.8
Classifier: Development Status :: 3 - Alpha
Classifier: Intended Audience :: Developers
Classifier: Programming Language :: Python :: 3.9
Classifier: Programming Language :: Python :: 3.10
Classifier: Programming Language :: Python :: 3.11
Classifier: Programming Language :: Python :: 3.12
Project-URL: Documentation, https://benrutter.github.io/ufo-tools/index.html
Project-URL: Homepage, https://benrutter.github.io/ufo-tools/index.html
Project-URL: Issues, https://github.com/benrutter/ufo-tools/issues
Project-URL: Repository, https://github.com/benrutter/ufo-tools
